pypdfzipcrack/__init__.py
pypdfzipcrack/pdfzipcrack.py
pypdfzipcrack-1.1.dist-info/METADATA
pypdfzipcrack-1.1.dist-info/WHEEL
pypdfzipcrack-1.1.dist-info/entry_points.txt
pypdfzipcrack-1.1.dist-info/top_level.txt
pypdfzipcrack-1.1.dist-info/RECORD
