Metadata-Version: 2.1
Name: pypdfzipcrack
Version: 1.1
Summary: A tool to crack encrypted PDF and ZIP files.
Classifier: Programming Language :: Python :: 3
Classifier: License :: OSI Approved :: MIT License
Classifier: Operating System :: OS Independent
Requires-Python: >=3.6
Requires-Dist: PyPDF2
Requires-Dist: pyzipper
